okada_wrapper-24.6.15.dist-info/METADATA
okada_wrapper-24.6.15.dist-info/WHEEL
okada_wrapper/DC3D.cpython-312-darwin.so
okada_wrapper/__init__.py
okada_wrapper/okada_wrapper.py
okada_wrapper-24.6.15.dist-info/RECORD
