Metadata-Version: 2.1
Name: okada_wrapper
Version: 24.6.15
Summary: Python and MATLAB wrappers for the Okada Green's function codes
Keywords: okada,elastic,halfspace
Author-Email: Ben Thompson <t.ben.thompson@gmail.com>
License: MIT
Requires-Python: >=3.8
Requires-Dist: numpy
